<Properties StartupConfiguration="{4207A5CF-DF47-48E9-BCE3-D7E0E34466B4}|Default">
  <MonoDevelop.Ide.ItemProperties.MyCardSession PreferredExecutionTarget="/Applications/Google Chrome.app" />
  <MonoDevelop.Ide.Workbench>
    <Pads>
      <Pad Id="ProjectPad">
        <State name="__root__">
          <Node name="MyCardSession" expanded="True">
            <Node name="MyCardSession" expanded="True" selected="True">
              <Node name="Dependencies" expanded="True">
                <Node name="PackageDependencies" expanded="True" />
              </Node>
              <Node name="Controllers" expanded="True" />
              <Node name="Helpers" expanded="True" />
              <Node name="Models" expanded="True" />
              <Node name="Views" expanded="True">
                <Node name="Cart" expanded="True" />
                <Node name="Product" expanded="True" />
                <Node name="Shared" expanded="True" />
              </Node>
              <Node name="wwwroot" expanded="True">
                <Node name="lib" expanded="True" />
              </Node>
            </Node>
          </Node>
        </State>
      </Pad>
    </Pads>
  </MonoDevelop.Ide.Workbench>
  <MonoDevelop.Ide.DebuggingService.PinnedWatches />
  <MonoDevelop.Ide.Workspace ActiveConfiguration="Debug" />
  <MonoDevelop.Ide.DebuggingService.Breakpoints>
    <BreakpointStore />
  </MonoDevelop.Ide.DebuggingService.Breakpoints>
  <MultiItemStartupConfigurations />
</Properties>